HISTORY.rst
LICENSE
MANIFEST.in
README.rst
requirements.txt
setup.py
robobrowser/__init__.py
robobrowser/browser.py
robobrowser/cache.py
robobrowser/compat.py
robobrowser/exceptions.py
robobrowser/helpers.py
robobrowser/ordereddict.py
robobrowser/responses.py
robobrowser.egg-info/PKG-INFO
robobrowser.egg-info/SOURCES.txt
robobrowser.egg-info/dependency_links.txt
robobrowser.egg-info/not-zip-safe
robobrowser.egg-info/requires.txt
robobrowser.egg-info/top_level.txt
robobrowser/forms/__init__.py
robobrowser/forms/fields.py
robobrowser/forms/form.py
tests/__init__.py
tests/fixtures.py
tests/test_browser.py
tests/test_cache.py
tests/test_forms.py
tests/test_helpers.py
tests/utils.py